th2c/__init__.py
th2c/__main__.py
th2c/client.py
th2c/config.py
th2c/connection.py
th2c/exceptions.py
th2c/flowcontrol.py
th2c/response.py
th2c/stream.py
th2c-0.3.1.dist-info/METADATA
th2c-0.3.1.dist-info/RECORD
th2c-0.3.1.dist-info/WHEEL
th2c-0.3.1.dist-info/top_level.txt
