Metadata-Version: 2.1
Name: th2c
Version: 0.3.1
Summary: HTTP/2 Async Client written with h2, for tornado
Home-page: https://github.com/vladmunteanu/th2c
Author: Vlad Stefan Munteanu
Author-email: vladstefanmunteanu@gmail.com
License: MIT License
Platform: UNKNOWN
Classifier: Development Status :: 4 - Beta
Classifier: Intended Audience :: Developers
Classifier: License :: OSI Approved :: MIT License
Classifier: Programming Language :: Python
Classifier: Programming Language :: Python :: 2
Classifier: Programming Language :: Python :: 2.7
Classifier: Programming Language :: Python :: Implementation :: CPython
Requires-Dist: tornado (>=4.2)
Requires-Dist: h2 (==3.0.1)
